bread_engine/__init__.py
bread_engine/color.py
bread_engine/engine.py
bread_engine/entities.py
bread_engine/keyhandler.py
bread_engine-0.1.1.dist-info/METADATA
bread_engine-0.1.1.dist-info/WHEEL
bread_engine-0.1.1.dist-info/RECORD
