Metadata-Version: 2.4
Name: bread_engine
Version: 0.1.1
Summary: A python game engine using PyGame
Project-URL: Homepage, https://github.com/maghje13/bread_engine
Project-URL: PyPI, https://pypi.org/project/bread-engine
Author-email: maghje13 <13maghje@gmail.com>
License-Expression: MIT
Classifier: Operating System :: OS Independent
Classifier: Programming Language :: Python :: 3
Requires-Python: >=3.8
